generate/__init__.py
generate/generate.py
generate/wordlists/eff_large_wordlist
bk_generator-1.0.21.dist-info/LICENSE
bk_generator-1.0.21.dist-info/METADATA
bk_generator-1.0.21.dist-info/WHEEL
bk_generator-1.0.21.dist-info/entry_points.txt
bk_generator-1.0.21.dist-info/top_level.txt
bk_generator-1.0.21.dist-info/RECORD
